titrationFitter/__init__.py
titrationFitter/titrationFitter.py
titrationFitter-0.1.2.dist-info/LICENSE.txt
titrationFitter-0.1.2.dist-info/METADATA
titrationFitter-0.1.2.dist-info/WHEEL
titrationFitter-0.1.2.dist-info/top_level.txt
titrationFitter-0.1.2.dist-info/RECORD
