Metadata-Version: 2.1
Name: titrationFitter
Version: 0.1.2
Summary: Extracts binding constant from titration experiments
Home-page: https://gitlab.epfl.ch/dux/titration-fitting/
Author: Frédéric Dux
Author-email: duxfrederic@gmail.com
License: MIT
Platform: UNKNOWN
Requires-Python: >3.7.0
Requires-Dist: numpy
Requires-Dist: scipy
Requires-Dist: matplotlib
